<?xml version="1.0"?>
<!--
/**
* @author      Tsvetan Stoychev <tsvetan.stoychev@extendix.com>
* @website     http://www.extendix.com
* @license     http://opensource.org/licenses/osl-3.0.php Open Software Licence 3.0 (OSL-3.0)
*/
-->
<config>
    <menu>
        <speedy_simple_shipping translate="title" module="speedy_simple_shipping">
            <title>Speedy.bg</title>
            <sort_order>30</sort_order>
            <children>
                <report translate="title" module="speedy_simple_shipping">
                    <title>Address Book</title>
                    <action>adminhtml/speedySimpleShipping_addressBook</action>
                    <sort_order>0</sort_order>
                </report>
            </children>
        </speedy_simple_shipping>
    </menu>
    <acl>
        <resources>
            <admin>
                <children>
                    <speedy_simple_shipping translate="title" module="speedy_simple_shipping">
                        <title>Speedy.bg</title>
                        <sort_order>30</sort_order>
                        <children>
                            <report translate="title">
                                <title>Address Book</title>
                            </report>
                        </children>
                    </speedy_simple_shipping>
                    <system>
                        <children>
                            <config>
                                <children>
                                    <carriers>
                                        <children>
                                            <speedy_simple_shipping translate="title" module="speedy_simple_shipping">
                                                <title>Speedy Shipping</title>
                                                <sort_order>100</sort_order>
                                            </speedy_simple_shipping>
                                        </children>
                                    </carriers>
                                </children>
                            </config>
                        </children>
                    </system>
                </children>
            </admin>
        </resources>
    </acl>
</config>